wavecracker/__init__.py
wavecracker/signalanalyzer.py
wavecracker/conf/logging.conf
wavecracker/conf/sa_tables.yaml
wavecracker/conf/signal_analyzer.yaml
wavecracker/demo/launch_demo.py
wavecracker/docs/SA_DEBUG_how_to.txt
wavecracker/docs/change_log.txt
wavecracker/docs/cmdline_args_reference.txt
wavecracker/docs/csv_discard_policies.txt
wavecracker/docs/known_issues.txt
wavecracker/docs/setup.txt
wavecracker/docs/user_guide.txt
wavecracker/docs/win_script_example.txt
wavecracker/docs/writing_an_sa_loader.txt
wavecracker/util/boot_helper.py
wavecracker/util/common_util.py
wavecracker/util/config_tables_util.py
wavecracker/util/config_util.py
wavecracker/util/data_loader.py
wavecracker/util/data_loader_resolution.py
wavecracker/util/data_preproc.py
wavecracker/util/file_util.py
wavecracker/util/float_separators_util.py
wavecracker/util/ft_calculator.py
wavecracker/util/grid_iterator.py
wavecracker/util/header_detection.py
wavecracker/util/hw_diagnostics.py
wavecracker/util/logging_util.py
wavecracker/util/plot_manager.py
wavecracker/util/plot_save.py
wavecracker/util/plot_window_wrap.py
wavecracker/util/polynt_calc.py
wavecracker/util/dataloaders/common_dataload_util.py
wavecracker/util/dataloaders/loader_audio_pydub.py
wavecracker/util/dataloaders/loader_csv_1.py
wavecracker/util/dataloaders/loader_mp3_pydub.py
wavecracker/util/dataloaders/loader_mp4_pydub.py
wavecracker/util/dataloaders/loader_wav_pydub.py
wavecracker/util/dataloaders/loader_wmv_moviepy.py
wavecracker/util/dataloaders/multichannel_util.py
wavecracker/util/plot/plot_3d_spectrogram.py
wavecracker/util/plot/plot_ft.py
wavecracker/util/plot/plot_ftphase.py
wavecracker/util/plot/plot_histogram.py
wavecracker/util/plot/plot_instfreq.py
wavecracker/util/plot/plot_origsignal.py
wavecracker/util/plot/plot_psd.py
wavecracker/util/plot/plot_qq.py
wavecracker/util/plot/plot_spectrogram.py
wavecracker/util/plot/plot_util.py
wavecracker/util/plot/plot_wavelet.py
wavecracker-9.1.1.dist-info/METADATA
wavecracker-9.1.1.dist-info/WHEEL
wavecracker-9.1.1.dist-info/licenses/LICENSE
wavecracker-9.1.1.dist-info/RECORD
