Metadata-Version: 2.3
Name: wavecracker
Version: 9.1.1
Summary: Python batch tool for signal time/frequency analysis
Author-email: "Matteo Pi." <thx.1138@inwind.it>
License-File: LICENSE
Classifier: Development Status :: 5 - Production/Stable
Classifier: Environment :: Console
Classifier: Intended Audience :: Developers
Classifier: Intended Audience :: End Users/Desktop
Classifier: Intended Audience :: Science/Research
Classifier: License :: OSI Approved :: MIT License
Classifier: Natural Language :: English
Classifier: Operating System :: Microsoft :: Windows
Classifier: Operating System :: OS Independent
Classifier: Programming Language :: Python
Classifier: Topic :: File Formats
Classifier: Topic :: Scientific/Engineering
Classifier: Topic :: Software Development
Requires-Python: >=3.7
Requires-Dist: chardet>=4.0.0
Requires-Dist: matplotlib>=3.7.1
Requires-Dist: numpy>=1.23.5
Requires-Dist: pandas>=2.0.1
Requires-Dist: pyyaml>=6.0
Requires-Dist: scipy>=1.10.1
Provides-Extra: audio
Requires-Dist: moviepy>=1.0.3; extra == 'audio'
Requires-Dist: pydub>=0.25.1; extra == 'audio'
Provides-Extra: hwdiagnostics
Requires-Dist: psutil>=5.9.5; extra == 'hwdiagnostics'
Provides-Extra: wavelet
Requires-Dist: pywavelets>=1.4.1; extra == 'wavelet'
